{
  "id": "smb",
  "title": "SMB",
  "shortName": "SMB",
  "type": "protocol",
  "osiLayer": 5,
  "category": "osi_layer",
  "port": 445,
  "transport": "TCP",
  "description": "Server Message Block — file, printer, and resource sharing protocol for Windows networks.",
  "fullExplanation": "SMB (Server Message Block) is a network file sharing protocol that allows applications to read and write to files and request services from server programs. It runs directly over TCP port 445 (modern) or over NetBIOS on port 139 (legacy). SMB is the foundation of Windows file sharing, printer sharing, and named pipes. SMBv3 (Windows 8+) added encryption, multichannel support, and improved performance.",
  "keyFacts": [
    "Port 445: Direct SMB over TCP (modern)",
    "Port 139: SMB over NetBIOS (legacy)",
    "Used for Windows file and printer sharing",
    "SMBv1 vulnerable to EternalBlue (WannaCry exploit)",
    "SMBv2 introduced in Windows Vista — reduced chattiness",
    "SMBv3 added end-to-end encryption (Windows 8/Server 2012)",
    "CIFS is an older dialect of SMB",
    "Samba implements SMB on Linux/Unix"
  ],
  "versions": [
    { "version": "SMBv1 / CIFS", "year": 1992, "feature": "Original, verbose, vulnerable to EternalBlue" },
    { "version": "SMBv2", "year": 2006, "feature": "Windows Vista — fewer round trips, better performance" },
    { "version": "SMBv2.1", "year": 2008, "feature": "Windows 7 — opportunistic locking improvements" },
    { "version": "SMBv3.0", "year": 2012, "feature": "Windows 8 — encryption, multichannel, RDMA" },
    { "version": "SMBv3.1.1", "year": 2015, "feature": "Windows 10 — pre-auth integrity, AES-128-GCM" }
  ],
  "cybersecurity": {
    "attacks": ["mitm", "arp-spoofing"],
    "defenses": ["firewall", "ids-ips", "vpn"]
  },
  "relatedConcepts": ["netbios", "CIFS", "Samba", "layer5-session"],
  "dependsOn": ["tcp", "ipv4"],
  "visualization": { "color": "#8b5cf6", "icon": "📁", "nodeType": "leaf" }
}
